anaconda_ai/__init__.py
anaconda_ai/_version.py
anaconda_ai/cli.py
anaconda_ai/config.py
anaconda_ai/exceptions.py
anaconda_ai/py.typed
anaconda_ai/utils.py
anaconda_ai/clients/__init__.py
anaconda_ai/clients/ai_navigator.py
anaconda_ai/clients/base.py
anaconda_ai/integrations/Anaconda_Logo.png
anaconda_ai/integrations/langchain.py
anaconda_ai/integrations/litellm.py
anaconda_ai/integrations/llama_index.py
anaconda_ai/integrations/llm.py
anaconda_ai/integrations/panel.py
anaconda_ai-0.4.2.dist-info/METADATA
anaconda_ai-0.4.2.dist-info/WHEEL
anaconda_ai-0.4.2.dist-info/entry_points.txt
anaconda_ai-0.4.2.dist-info/licenses/LICENSE
anaconda_ai-0.4.2.dist-info/RECORD
