Metadata-Version: 2.4
Name: anaconda-ai
Version: 0.4.2
Summary: Download and launch curated models from Anaconda
License: BSD-3-Clause
License-File: LICENSE
Requires-Python: >=3.9
Requires-Dist: anaconda-auth>=0.8
Requires-Dist: anaconda-cli-base>=0.5
Requires-Dist: click<8.2
Requires-Dist: openai
Requires-Dist: packaging
Requires-Dist: platformdirs
Requires-Dist: pydantic>=2
Requires-Dist: rich
Requires-Dist: ruamel-yaml
Requires-Dist: typer
Provides-Extra: all
Requires-Dist: httpx; extra == 'all'
Requires-Dist: langchain-openai>=0.2.8; extra == 'all'
Requires-Dist: litellm; extra == 'all'
Requires-Dist: llama-index-embeddings-openai; extra == 'all'
Requires-Dist: llama-index-llms-openai; extra == 'all'
Requires-Dist: llm>=0.22; extra == 'all'
Requires-Dist: numpy; extra == 'all'
Requires-Dist: panel>=1.5.4; (python_version >= '3.10') and extra == 'all'
Provides-Extra: dev
Requires-Dist: mypy; extra == 'dev'
Requires-Dist: pytest; extra == 'dev'
Requires-Dist: pytest-cov; extra == 'dev'
Requires-Dist: pytest-mock; extra == 'dev'
Requires-Dist: tox; extra == 'dev'
Requires-Dist: types-requests; extra == 'dev'
Provides-Extra: langchain
Requires-Dist: langchain-openai>=0.2.8; extra == 'langchain'
Provides-Extra: litellm
Requires-Dist: litellm; extra == 'litellm'
Provides-Extra: llama-index
Requires-Dist: llama-index-embeddings-openai; extra == 'llama-index'
Requires-Dist: llama-index-llms-openai; extra == 'llama-index'
Provides-Extra: llm
Requires-Dist: llm>=0.22; extra == 'llm'
Provides-Extra: panel
Requires-Dist: httpx; extra == 'panel'
Requires-Dist: numpy; extra == 'panel'
Requires-Dist: panel>=1.5.4; (python_version >= '3.10') and extra == 'panel'
Provides-Extra: publish
Requires-Dist: build; extra == 'publish'
Requires-Dist: twine; extra == 'publish'
Requires-Dist: wheel; extra == 'publish'
